cjops/__init__.py
cjops/__version__.py
cjops/command.py
cjops/csv.py
cjops/domain.py
cjops/email.py
cjops/excel.py
cjops/info.py
cjops/qw.py
cjops/sql.py
cjops/ssh.py
cjops/thread.py
cjops/time.py
cjops/aliyun/__init__.py
cjops/aliyun/sls.py
cjops/template/__init__.py
cjops/template/fastapi_temp.py
cjops/template/request_get.py
cjops/template/request_post.py
cjops/template/send_qw_markdown.py
cjops/utils/__init__.py
cjops/utils/_base64_info.py
cjops/utils/_clipboard.py
cjops/utils/_fernet.py
cjops/utils/_md5_encrypt.py
cjops/utils/_toast.py
cjops/utils/_tqdm_encap.py
cjops-1.0.87.dist-info/LICENSE
cjops-1.0.87.dist-info/METADATA
cjops-1.0.87.dist-info/WHEEL
cjops-1.0.87.dist-info/top_level.txt
cjops-1.0.87.dist-info/RECORD
