Metadata-Version: 2.1
Name: cjops
Version: 1.0.87
Summary: cj ops.
Author: chenxing
Author-email: chenxing@cjdropshipping.co
Classifier: Programming Language :: Python :: 3
Classifier: License :: OSI Approved :: MIT License
Classifier: Operating System :: OS Independent
Requires-Python: >=3
License-File: LICENSE
Requires-Dist: aliyun-log-python-sdk ==0.8.15
Requires-Dist: requests >=2.27.1
Requires-Dist: loguru >=0.6.0
Requires-Dist: dnspython >=2.3.0
Requires-Dist: pandas >=1.1.5
Requires-Dist: pendulum >=2.1.2
Requires-Dist: pymysql >=1.0.2
Requires-Dist: openpyxl >=3.1.2
Requires-Dist: yagmail >=0.15.293
Requires-Dist: tqdm >=4.66.2
Requires-Dist: pyperclip >=1.8.2
Requires-Dist: emoji >=2.11.1
Requires-Dist: paramiko ==3.4.0
Requires-Dist: cryptography
